README.rst
setup.py
z7z8/__init__.py
z7z8/compat.py
z7z8/cookie_utils.py
z7z8.egg-info/PKG-INFO
z7z8.egg-info/SOURCES.txt
z7z8.egg-info/dependency_links.txt
z7z8.egg-info/requires.txt
z7z8.egg-info/top_level.txt