Metadata-Version: 1.0
Name: z7z8
Version: 0.0.1
Summary: Some python utils.
Home-page: https://github.com/ll1l11/z7z8
Author: ll1l11
Author-email: ll1l11@qq.com
License: UNKNOWN
Platform: UNKNOWN
